kics-3.8.1-py3.7-nspkg.pth
kelvin/kics/__init__.py
kelvin/kics/kics.py
kics-3.8.1.dist-info/METADATA
kics-3.8.1.dist-info/WHEEL
kics-3.8.1.dist-info/entry_points.txt
kics-3.8.1.dist-info/namespace_packages.txt
kics-3.8.1.dist-info/top_level.txt
kics-3.8.1.dist-info/zip-safe
kics-3.8.1.dist-info/RECORD
