Metadata-Version: 2.1
Name: kics
Version: 3.8.1
Summary: KICS
Home-page: https://kelvininc.com/
Author: Kelvin Inc
Author-email: engineering@kelvininc.com
License: UNKNOWN
Platform: any
Classifier: Operating System :: OS Independent
Classifier: Programming Language :: Python :: 3.7
Classifier: Programming Language :: Python :: 3.8
Classifier: Programming Language :: Python :: 3.9
Requires-Python: <3.10,>=3.7.0
Requires-Dist: click (==7.1.2)
Requires-Dist: kelvin-sdk (==6.2.1)
